twos_complement/__init__.py
twos_complement/test.py
twos_complement/twos_complement.py
twos_complement-0.0.1.dist-info/METADATA
twos_complement-0.0.1.dist-info/WHEEL
twos_complement-0.0.1.dist-info/top_level.txt
twos_complement-0.0.1.dist-info/RECORD
