Metadata-Version: 2.1
Name: twos-complement
Version: 0.0.1
Summary: converts binary to twos complements binary. 
Home-page: https://github.com/micfun123/twos-complement
Author: Michael Parker
Author-email: michaelrbparker@protonmail.com
License: UNKNOWN
Platform: UNKNOWN
